MANIFEST.in
README.md
setup.py
pandan/__init__.py
pandan/pandan.py
pandan.egg-info/PKG-INFO
pandan.egg-info/SOURCES.txt
pandan.egg-info/dependency_links.txt
pandan.egg-info/not-zip-safe
pandan.egg-info/top_level.txt