Metadata-Version: 2.1
Name: pandan
Version: 0.1
Summary: A small library to make decisions out of sequences of evidences
Home-page: https://github.com/zebehn/pandan.git
Author: Minsu Jang
Author-email: minsu@etri.re.kr
License: BSD 3-Clause
Keywords: sequential decision making
Platform: UNKNOWN
Classifier: Development Status :: 2 - Pre-Alpha
Classifier: License :: OSI Approved :: BSD License
Classifier: Programming Language :: Python :: 3
